softpandas/__init__.py
softpandas/core/__init__.py
softpandas/core/data_types.py
softpandas/core/soft_dataframe.py
softpandas/core/utils.py
softpandas/embedders/__init__.py
softpandas/embedders/clip_embedder.py
softpandas/embedders/embedder.py
softpandas/embedders/sentence_transformer_embedder.py
softpandas-0.1.dist-info/LICENSE
softpandas-0.1.dist-info/METADATA
softpandas-0.1.dist-info/WHEEL
softpandas-0.1.dist-info/top_level.txt
softpandas-0.1.dist-info/RECORD
