Metadata-Version: 2.1
Name: softpandas
Version: 0.1
Summary: An easy to use semantic (soft) querying on pandas dataframes.
Author-email: Ido Ben-Shaul <ido.benshaul@gmail.com>
License: Apache License
Project-URL: Homepage, https://github.com/idobenshaul10/SoftPandas
Project-URL: Issues, https://github.com/idobenshaul10/SoftPandas/issues
Keywords: Semantic Search,Pandas,Vector Database
Classifier: Development Status :: 3 - Alpha
Classifier: Topic :: Scientific/Engineering :: Artificial Intelligence
Classifier: Environment :: Console
Classifier: Programming Language :: Python :: 3.11
Requires-Python: >=3.10
License-File: LICENSE
Requires-Dist: pandas
Requires-Dist: numpy
Requires-Dist: open-clip-torch
Requires-Dist: setuptools
Requires-Dist: argparse
Requires-Dist: sentence-transformers
